plaincities/__init__.py
plaincities/countries.py
plaincities/generator.py
plaincities/_values/__init__.py
plaincities/_values/constants.py
plaincities/_values/ar/AD_ar.py
plaincities/_values/ar/AE_ar.py
plaincities/_values/ar/AF_ar.py
plaincities/_values/ar/AG_ar.py
plaincities/_values/ar/AI_ar.py
plaincities/_values/ar/AL_ar.py
plaincities/_values/ar/AM_ar.py
plaincities/_values/ar/AN_ar.py
plaincities/_values/ar/AO_ar.py
plaincities/_values/ar/AQ_ar.py
plaincities/_values/ar/AR_ar.py
plaincities/_values/ar/AS_ar.py
plaincities/_values/ar/AT_ar.py
plaincities/_values/ar/AU_ar.py
plaincities/_values/ar/AW_ar.py
plaincities/_values/ar/AX_ar.py
plaincities/_values/ar/AZ_ar.py
plaincities/_values/ar/BA_ar.py
plaincities/_values/ar/BB_ar.py
plaincities/_values/ar/BD_ar.py
plaincities/_values/ar/BE_ar.py
plaincities/_values/ar/BF_ar.py
plaincities/_values/ar/BG_ar.py
plaincities/_values/ar/BH_ar.py
plaincities/_values/ar/BI_ar.py
plaincities/_values/ar/BJ_ar.py
plaincities/_values/ar/BL_ar.py
plaincities/_values/ar/BM_ar.py
plaincities/_values/ar/BN_ar.py
plaincities/_values/ar/BO_ar.py
plaincities/_values/ar/BQ_ar.py
plaincities/_values/ar/BR_ar.py
plaincities/_values/ar/BS_ar.py
plaincities/_values/ar/BT_ar.py
plaincities/_values/ar/BV_ar.py
plaincities/_values/ar/BW_ar.py
plaincities/_values/ar/BY_ar.py
plaincities/_values/ar/BZ_ar.py
plaincities/_values/ar/CA_ar.py
plaincities/_values/ar/CC_ar.py
plaincities/_values/ar/CD_ar.py
plaincities/_values/ar/CF_ar.py
plaincities/_values/ar/CG_ar.py
plaincities/_values/ar/CH_ar.py
plaincities/_values/ar/CI_ar.py
plaincities/_values/ar/CK_ar.py
plaincities/_values/ar/CL_ar.py
plaincities/_values/ar/CM_ar.py
plaincities/_values/ar/CN_ar.py
plaincities/_values/ar/CO_ar.py
plaincities/_values/ar/CR_ar.py
plaincities/_values/ar/CS_ar.py
plaincities/_values/ar/CU_ar.py
plaincities/_values/ar/CV_ar.py
plaincities/_values/ar/CW_ar.py
plaincities/_values/ar/CX_ar.py
plaincities/_values/ar/CY_ar.py
plaincities/_values/ar/CZ_ar.py
plaincities_bracket-0.3.dist-info/LICENSE
plaincities_bracket-0.3.dist-info/METADATA
plaincities_bracket-0.3.dist-info/WHEEL
plaincities_bracket-0.3.dist-info/top_level.txt
plaincities_bracket-0.3.dist-info/RECORD
