Metadata-Version: 2.1
Name: plaincities-bracket
Version: 0.3
Summary: plaincities is a library of places in many languages. 
Author-email: Ufuk Kocolu <ufuk.kocolu@proton.me>
Project-URL: Homepage, https://github.com/ufukk/plaincities
Project-URL: Bug Tracker, https://github.com/ufukk/plaincities/issues
Classifier: Programming Language :: Python :: 3
Classifier: License :: OSI Approved :: MIT License
Classifier: Operating System :: OS Independent
Requires-Python: >=3.7
License-File: LICENSE
